AUTHORS
Changelog
LICENSE-GPL-2.0
LICENSE-MPL-RabbitMQ
MANIFEST.in
README.rst
TODO
setup.cfg
setup.py
pylibrabbitmq/.pylibrabbitmq_distmeta.h.swp
pylibrabbitmq/__init__.py
pylibrabbitmq/_amqstate.h
pylibrabbitmq/_rabbitmqmodule.c
pylibrabbitmq/_rabbitmqmodule.h
pylibrabbitmq/pylibrabbitmq_distmeta.h
pylibrabbitmq.egg-info/PKG-INFO
pylibrabbitmq.egg-info/SOURCES.txt
pylibrabbitmq.egg-info/dependency_links.txt
pylibrabbitmq.egg-info/not-zip-safe
pylibrabbitmq.egg-info/top_level.txt
pylibrabbitmq/tests/test_functional.py