Metadata-Version: 1.0
Name: pylibrabbitmq
Version: 0.5.0
Summary: Python bindings to librabbitmq-c
Home-page: http://github.com/ask/pylibrabbitmq
Author: Ask Solem
Author-email: ask@celeryproject.org
License: MPL
Platform: UNKNOWN
Classifier: Development Status :: 3 - Alpha
Classifier: Operating System :: OS Independent
Classifier: Programming Language :: C
Classifier: Intended Audience :: Developers
Classifier: License :: OSI Approved :: Mozilla Public License 1.0 (MPL)
Classifier: Topic :: Communications
Classifier: Topic :: System :: Networking
Classifier: Topic :: Software Development :: Libraries
